cli.py
semantic_similarity_cli-1.0.0.dist-info/LICENSE
semantic_similarity_cli-1.0.0.dist-info/METADATA
semantic_similarity_cli-1.0.0.dist-info/WHEEL
semantic_similarity_cli-1.0.0.dist-info/entry_points.txt
semantic_similarity_cli-1.0.0.dist-info/top_level.txt
semantic_similarity_cli-1.0.0.dist-info/RECORD
