Metadata-Version: 2.1
Name: semantic-similarity-cli
Version: 1.0.0
Summary: file: README.md
License: MIT License
Classifier: Programming Language :: Python :: 3
Classifier: License :: OSI Approved :: MIT License
Classifier: Operating System :: OS Independent
License-File: LICENSE
Requires-Dist: InstructorEmbedding ==1.0.1
Requires-Dist: sentence-transformers >=2.2.0
Requires-Dist: numpy
Requires-Dist: tqdm
